pgeocode.py
pgeocode-0.5.0.dist-info/LICENSE
pgeocode-0.5.0.dist-info/METADATA
pgeocode-0.5.0.dist-info/WHEEL
pgeocode-0.5.0.dist-info/top_level.txt
pgeocode-0.5.0.dist-info/RECORD
