Metadata-Version: 2.1
Name: pgeocode
Version: 0.5.0
Summary: Postal code geocoding
Author: Roman Yurchak
Author-email: roman.yurchak@symerio.com
License: BSD
Classifier: Intended Audience :: Science/Research
Classifier: Intended Audience :: Developers
Classifier: License :: OSI Approved :: BSD License
Classifier: Programming Language :: Python
Classifier: Programming Language :: Python :: 3
Classifier: Topic :: Software Development
Classifier: Operating System :: POSIX
Classifier: Operating System :: Unix
Requires-Python: >=3.10
License-File: LICENSE
Requires-Dist: requests
Requires-Dist: numpy
Requires-Dist: pandas
Provides-Extra: fuzzy
Requires-Dist: thefuzz; extra == "fuzzy"
